pyjsx/__init__.py
pyjsx/__main__.py
pyjsx/auto_setup.py
pyjsx/codec_hook.py
pyjsx/elements.py
pyjsx/import_hook.py
pyjsx/jsx.py
pyjsx/mypy.py
pyjsx/py.typed
pyjsx/tokenizer.py
pyjsx/transpiler.py
pyjsx/util.py
python_jsx-0.4.0.dist-info/METADATA
python_jsx-0.4.0.dist-info/WHEEL
python_jsx-0.4.0.dist-info/licenses/LICENSE
python_jsx-0.4.0.dist-info/RECORD
