Metadata-Version: 2.4
Name: python-jsx
Version: 0.4.0
Summary: JSX transpiler for Python
Project-URL: Homepage, https://github.com/tomasr8/pyjsx
Project-URL: GitHub, https://github.com/tomasr8/pyjsx
Author-email: Tomas Roun <tomas.roun8@gmail.com>
License-Expression: Apache-2.0
License-File: LICENSE
Keywords: JSX,React,template-engine,transpiler
Classifier: Operating System :: OS Independent
Classifier: Programming Language :: Python :: 3
Classifier: Programming Language :: Python :: 3.10
Classifier: Programming Language :: Python :: 3.11
Classifier: Programming Language :: Python :: 3.12
Classifier: Programming Language :: Python :: 3.13
Classifier: Programming Language :: Python :: 3.14
Requires-Python: >=3.10
